whatswhere/__init__.py
whatswhere/cli.py
whatswhere/config.py
whatswhere/env_tools.py
whatswhere/github_tools.py
whatswhere/grid.py
whatswhere/local_git.py
whatswhere/render.py
whatswhere/utils.py
whatswhere-1.0.1.dist-info/DESCRIPTION.rst
whatswhere-1.0.1.dist-info/entry_points.txt
whatswhere-1.0.1.dist-info/METADATA
whatswhere-1.0.1.dist-info/metadata.json
whatswhere-1.0.1.dist-info/RECORD
whatswhere-1.0.1.dist-info/top_level.txt
whatswhere-1.0.1.dist-info/WHEEL
